src/fibery_mcp_server/__init__.py
src/fibery_mcp_server/__main__.py
src/fibery_mcp_server/fibery_client.py
src/fibery_mcp_server/server.py
src/fibery_mcp_server/utils.py
src/fibery_mcp_server/tools/__init__.py
src/fibery_mcp_server/tools/create_entity.py
src/fibery_mcp_server/tools/current_date.py
src/fibery_mcp_server/tools/database.py
src/fibery_mcp_server/tools/query.py
src/fibery_mcp_server/tools/schema.py
src/fibery_mcp_server/tools/update_entity.py
src/fibery_mcp_server/tools/descriptions/create_entity
src/fibery_mcp_server/tools/descriptions/query
src/fibery_mcp_server/tools/descriptions/update_entity
tests/fibery_service_test.py
orange_fibery_mcp_server-0.1.0.dist-info/METADATA
orange_fibery_mcp_server-0.1.0.dist-info/WHEEL
orange_fibery_mcp_server-0.1.0.dist-info/entry_points.txt
orange_fibery_mcp_server-0.1.0.dist-info/RECORD
