Metadata-Version: 2.4
Name: orange-fibery-mcp-server
Version: 0.1.0
Summary: Add your description here
Requires-Python: >=3.10
Requires-Dist: click>=8.1.8
Requires-Dist: httpx>=0.28.1
Requires-Dist: mcp[cli]>=1.4.1
Requires-Dist: pydantic>=2.10.6
Requires-Dist: python-dotenv>=1.0.1
